AUTHORS.md
LICENSE
MANIFEST.in
README.md
setup.cfg
setup.py
versioneer.py
berteley_test/__init__.py
berteley_test/_version.py
berteley_test/berteley_test.py
berteley_test.egg-info/PKG-INFO
berteley_test.egg-info/SOURCES.txt
berteley_test.egg-info/dependency_links.txt
berteley_test.egg-info/not-zip-safe
berteley_test.egg-info/requires.txt
berteley_test.egg-info/top_level.txt
docs/Makefile
docs/make.bat
docs/source/conf.py
tests/__init__.py
tests/test_berteley_test.py