Metadata-Version: 2.1
Name: berteley-test
Version: 0.0.2
Summary: Example description.
Home-page: https://github.com/ericchagnon15/berteley_test
Author: Eric Chagnon
Author-email: echagnon@lbl.gov
License: BSD license
Keywords: berteley_test
Classifier: Development Status :: 2 - Pre-Alpha
Classifier: Natural Language :: English
Classifier: Programming Language :: Python :: 3
Requires-Python: >=3.8
Provides-Extra: tests
Provides-Extra: docs
License-File: LICENSE
License-File: AUTHORS.md
